xontrib/pipeliner/__init__.py
xontrib/pipeliner/parallel.py
xontrib_pipeliner_asttokens/__init__.py
xontrib_pipeliner_asttokens/asttokens.py
xontrib_pipeliner_asttokens/line_numbers.py
xontrib_pipeliner_asttokens/mark_tokens.py
xontrib_pipeliner_asttokens/util.py
xontrib_pipeliner_asttokens/version.py
xontrib_pipeliner-0.5.0.dist-info/LICENSE
xontrib_pipeliner-0.5.0.dist-info/METADATA
xontrib_pipeliner-0.5.0.dist-info/WHEEL
xontrib_pipeliner-0.5.0.dist-info/top_level.txt
xontrib_pipeliner-0.5.0.dist-info/RECORD
