Metadata-Version: 2.1
Name: xontrib-pipeliner
Version: 0.5.0
Summary: Easily process the lines using pipes in xonsh.
Home-page: https://github.com/anki-code/xontrib-pipeliner
Author: anki
Author-email: author@example.com
License: BSD
Project-URL: Documentation, https://github.com/anki-code/xontrib-pipeliner/blob/master/README.md
Project-URL: Code, https://github.com/anki-code/xontrib-pipeliner
Project-URL: Issue tracker, https://github.com/anki-code/xontrib-pipeliner/issues
Platform: any
Classifier: Environment :: Console
Classifier: Intended Audience :: End Users/Desktop
Classifier: Operating System :: OS Independent
Classifier: Programming Language :: Python
Classifier: Programming Language :: Unix Shell
Classifier: Topic :: System :: Shells
Classifier: Topic :: System :: System Shells
Classifier: Topic :: Terminals
Classifier: Topic :: System :: Networking
Classifier: License :: OSI Approved :: BSD License
Requires-Python: >=3.6
License-File: LICENSE
Requires-Dist: xonsh
Requires-Dist: six
